orchestrator/__init__.py
orchestrator/api/__init__.py
orchestrator/api/rest.py
orchestrator/api/dependencies/__init__.py
orchestrator/api/dependencies/validation.py
orchestrator/api/routers/__init__.py
orchestrator/api/routers/latest/__init__.py
orchestrator/api/routers/latest/latest.py
orchestrator/api/routers/v0/__init__.py
orchestrator/api/routers/v0/v0.py
orchestrator/api/routers/v0/actuators/__init__.py
orchestrator/api/routers/v0/actuators/actuators.py
orchestrator/api/routers/v0/actuators/experiments/__init__.py
orchestrator/api/routers/v0/actuators/experiments/experiments.py
orchestrator/api/routers/v0/actuators/experiments/requests/__init__.py
orchestrator/api/routers/v0/actuators/experiments/requests/requests.py
orchestrator/api/routers/v0/experiments/__init__.py
orchestrator/api/routers/v0/experiments/experiments.py
orchestrator/api/state/__init__.py
orchestrator/api/state/actuators.py
orchestrator/api/state/queue.py
orchestrator/cli/__init__.py
orchestrator/cli/commands/__init__.py
orchestrator/cli/commands/context.py
orchestrator/cli/commands/create.py
orchestrator/cli/commands/delete.py
orchestrator/cli/commands/describe.py
orchestrator/cli/commands/edit.py
orchestrator/cli/commands/get.py
orchestrator/cli/commands/show.py
orchestrator/cli/commands/show_details.py
orchestrator/cli/commands/show_entities.py
orchestrator/cli/commands/show_related.py
orchestrator/cli/commands/show_requests.py
orchestrator/cli/commands/show_results.py
orchestrator/cli/commands/show_summary.py
orchestrator/cli/commands/template.py
orchestrator/cli/commands/upgrade.py
orchestrator/cli/commands/version.py
orchestrator/cli/core/__init__.py
orchestrator/cli/core/cli.py
orchestrator/cli/core/config.py
orchestrator/cli/exceptions/__init__.py
orchestrator/cli/exceptions/actuators.py
orchestrator/cli/exceptions/handlers.py
orchestrator/cli/models/__init__.py
orchestrator/cli/models/choice.py
orchestrator/cli/models/parameters.py
orchestrator/cli/models/space.py
ado_core-1.4.1.dist-info/METADATA
ado_core-1.4.1.dist-info/WHEEL
ado_core-1.4.1.dist-info/entry_points.txt
ado_core-1.4.1.dist-info/licenses/LICENSE
ado_core-1.4.1.dist-info/RECORD
