Metadata-Version: 2.4
Name: ado-core
Version: 1.4.1
Summary: ado is a unified platform for executing computational experiments at scale and analysing their results. It can be easily extended with new experiments or new analysis tools. It allows distributed teams of researchers and engineers to collaborate on projects, execute experiments, and share data.
Project-URL: Homepage, https://ibm.github.io/ado/
Project-URL: Repository, https://github.com/IBM/ado
Project-URL: Issues, https://github.com/IBM/ado/issues
Project-URL: Changelog, https://github.com/IBM/ado/blob/main/CHANGELOG.md
Author-email: "Michael A. Johnston" <michaelj@ie.ibm.com>
Maintainer-email: "Michael A. Johnston" <michaelj@ie.ibm.com>
License-File: LICENSE
Keywords: discovery,exploration,optimization,orchestration,ray
Classifier: Development Status :: 3 - Alpha
Classifier: Intended Audience :: Developers
Classifier: Programming Language :: Python :: 3.10
Classifier: Programming Language :: Python :: 3.11
Classifier: Programming Language :: Python :: 3.12
Classifier: Programming Language :: Python :: 3.13
Classifier: Topic :: Software Development :: Build Tools
Requires-Python: <3.14,>=3.10
Requires-Dist: build>=1.3.0
Requires-Dist: colorlog>=6.9.0
Requires-Dist: jsonpath-ng>=1.7.0
Requires-Dist: numpy
Requires-Dist: pandas>=2.2.0
Requires-Dist: py-markdown-table>=1.3.0
Requires-Dist: pydantic>=2.10
Requires-Dist: pymysql[rsa]>=1.1.1
Requires-Dist: pyyaml>=6.0.2
Requires-Dist: ray[serve]>=2.9
Requires-Dist: sqlalchemy>2
Requires-Dist: typer>=0.16.1
